nostromo_core/__init__.py
nostromo_core/engine.py
nostromo_core/models.py
nostromo_core/adapters/__init__.py
nostromo_core/adapters/anthropic.py
nostromo_core/adapters/memory.py
nostromo_core/adapters/openai.py
nostromo_core/ports/__init__.py
nostromo_core/ports/llm.py
nostromo_core/ports/memory.py
nostromo_core/theme/__init__.py
nostromo_core/theme/constants.py
nostromo_core/theme/errors.py
nostromo_core/theme/prompts.py
nostromo_core-0.1.0.dist-info/METADATA
nostromo_core-0.1.0.dist-info/WHEEL
nostromo_core-0.1.0.dist-info/RECORD
