Metadata-Version: 2.4
Name: nostromo-core
Version: 0.1.0
Summary: Core domain logic for MU-TH-UR 6000 chatbot
Author: Nostromo Crew
License: MIT
Keywords: aliens,chatbot,llm,mother
Requires-Python: >=3.11
Requires-Dist: pydantic>=2.0.0
Provides-Extra: all
Requires-Dist: anthropic>=0.40.0; extra == 'all'
Requires-Dist: openai>=1.0.0; extra == 'all'
Provides-Extra: anthropic
Requires-Dist: anthropic>=0.40.0; extra == 'anthropic'
Provides-Extra: openai
Requires-Dist: openai>=1.0.0; extra == 'openai'
